.DS_Store
graphix_ibmq/__init__.py
graphix_ibmq/clifford.py
graphix_ibmq/runner.py
graphix_ibmq/version.py
graphix_ibmq-0.0.4.dist-info/LICENSE
graphix_ibmq-0.0.4.dist-info/METADATA
graphix_ibmq-0.0.4.dist-info/WHEEL
graphix_ibmq-0.0.4.dist-info/top_level.txt
graphix_ibmq-0.0.4.dist-info/RECORD
